echocolor/__init__.py
echocolor/colorizer.py
echocolor/colors.py
echocolor/escape_codes.py
echocolor/terminal_echo.py
echocolor-2.0.0.dist-info/DESCRIPTION.rst
echocolor-2.0.0.dist-info/METADATA
echocolor-2.0.0.dist-info/RECORD
echocolor-2.0.0.dist-info/WHEEL
echocolor-2.0.0.dist-info/metadata.json
echocolor-2.0.0.dist-info/top_level.txt
