Metadata-Version: 2.0
Name: echocolor
Version: 2.0.0
Summary: Simple interface for printing colored text to a terminal
Home-page: https://gitlab.com/danielhones/echocolor
Author: Daniel Hones
Author-email: UNKNOWN
License: MIT
Keywords: terminal,ansi,print,color
Platform: UNKNOWN
Classifier: Programming Language :: Python :: 2.7
Classifier: Programming Language :: Python :: 3.4
Classifier: Programming Language :: Python :: 3.5
Classifier: Programming Language :: Python :: 3.6
